[
  {
    "id": 1242640,
    "reference": "",
    "board_key": "887595b735d68f0bc0b0b0535f7d8f7d158a3f4e",
    "board": {
      "key": "887595b735d68f0bc0b0b0535f7d8f7d158a3f4e",
      "name": "test_frontend",
      "type": "api",
      "subtype": "python",
      "environment": "production"
    },
    "name": "Senior software engineer",
    "url": "",
    "picture": null,
    "summary": "Be part of a team that builds impactful features for our customers and pros everyday\nCollaborate with product and business teams to review specs and breakdown features into releasable chunks and work on those features\nContribute to code reviews, architectural and design reviews, evangelize best engineering practices, and participate in Handy lunch & learn sessions\nBe part of our production on-call rotation to support what you built.\nA skillful engineer with at least 3+ years of full-time, hands-on experience in a web stack\nWell-versed in at least one object oriented programming language: Ruby, Python, etc.\nAlways eager to understand and solve impactful business problems\nA great collaborator with both technical and non-technical team members\nHave a good foundational knowledge of programming languages, databases, operating systems, data structures, algorithms, and complexity trade-offs\nHaving worked at or founded a growth-stage startup is a plus Compensation & Benefits\nCompetitive salary and equity commensurate with experience and performance\nFull medical, dental, vision package to fit your needs\nMonthly Handy credits\nUnlimited vacation policy; work hard and take time when you need it\nA fun office, always stocked with coffee, snacks and drinks; catered lunch and dinner, foosball, office events and team outings\nGround floor opportunity with the team\nThe rare opportunity to work with sharp, motivated teammates solving some of the most unique challenges and changing the world We are an equal opportunity employer and value diversity at our company. We do not discriminate on the basis of race, religion, color, national origin, gender, sexual orientation, age, marital status, veteran status, or disability status.",
    "location": {
      "text": "Paris, France",
      "lat": 48.856614,
      "lng": 2.3522219,
      "gmaps": null,
      "fields": []
    },
    "archive": null,
    "archived_at": null,
    "updated_at": "2023-06-12T17:24:18+0000",
    "created_at": "2023-06-12T17:24:18+0000",
    "sections": [],
    "culture": null,
    "responsibilities": null,
    "requirements": null,
    "benefits": null,
    "interviews": null,
    "skills": [
      {
        "name": "python",
        "value": null,
        "type": null
      },
      {
        "name": "javascript",
        "value": null,
        "type": null
      },
      {
        "name": "devops",
        "value": null,
        "type": null
      },
      {
        "name": "docker",
        "value": null,
        "type": null
      },
      {
        "name": "PHP",
        "value": null,
        "type": null
      }
    ],
    "languages": [],
    "certifications": [
      {
        "name": "PMP",
        "value": null,
        "type": null
      }
    ],
    "courses": [],
    "tasks": [
      {
        "name": "Develop and maintain company core product",
        "value": null,
        "type": null
      }
    ],
    "interests": [],
    "tags": [
      {
        "name": "Company",
        "value": "HrFlow.ai"
      },
      {
        "name": "Type",
        "value": "Full time"
      },
      {
        "name": "Relocation",
        "value": "remote"
      }
    ],
    "metadatas": [],
    "ranges_float": [],
    "ranges_date": [
      {
        "name": "",
        "value_min": "2023-06-12T22:59:59.999Z",
        "value_max": "2025-06-12T22:59:59.999Z"
      }
    ],
    "ref": {
      "current": {}
    }
  },
  {
    "id": 698219,
    "reference": null,
    "board_key": "887595b735d68f0bc0b0b0535f7d8f7d158a3f4e",
    "board": {
      "key": "887595b735d68f0bc0b0b0535f7d8f7d158a3f4e",
      "name": "test_frontend",
      "type": "api",
      "subtype": "python",
      "environment": "production"
    },
    "name": "Machine Learning Engineer",
    "url": "",
    "picture": null,
    "summary": "",
    "location": {
      "text": "Paris, France",
      "lat": 48.856614,
      "lng": 2.3522219,
      "gmaps": null,
      "fields": []
    },
    "archive": null,
    "archived_at": null,
    "updated_at": "2022-01-24T15:55:12+0000",
    "created_at": "2022-01-24T15:55:12+0000",
    "sections": [
      {
        "name": "",
        "title": "",
        "description": "3+ years hands-on experience as a data scientist.\nUnder the hood knowledge with a variety of ML algorithms.\nMSc. in Statistics, Computer Science, Mathematics or other quantitative field.\nAbility to work independently and deliver end-to-end output.\nTeam player, can-do attitude, collaborative, good communication skills"
      }
    ],
    "culture": null,
    "responsibilities": null,
    "requirements": null,
    "benefits": null,
    "interviews": null,
    "skills": [
      {
        "name": "python",
        "value": null,
        "type": null
      },
      {
        "name": "R",
        "value": null,
        "type": null
      },
      {
        "name": "data visualisation",
        "value": null,
        "type": null
      },
      {
        "name": "linear algebra",
        "value": null,
        "type": null
      },
      {
        "name": "machine learning",
        "value": null,
        "type": null
      },
      {
        "name": "deep learning ",
        "value": null,
        "type": null
      },
      {
        "name": "NLP",
        "value": null,
        "type": null
      }
    ],
    "languages": [
      {
        "name": "english",
        "value": null
      }
    ],
    "certifications": [],
    "courses": [],
    "tasks": [],
    "interests": [],
    "tags": [
      {
        "name": "company",
        "value": "HrFlow.ai"
      },
      {
        "name": "type",
        "value": "Full time"
      },
      {
        "name": "category",
        "value": "AI / Research & Development"
      }
    ],
    "metadatas": [],
    "ranges_float": [],
    "ranges_date": [
      {
        "name": "",
        "value_min": "2021-12-24T22:59:59.999Z",
        "value_max": "2023-12-24T22:59:59.999Z"
      }
    ],
    "ref": {
      "current": {}
    }
  },
  {
    "id": 698218,
    "reference": null,
    "board_key": "887595b735d68f0bc0b0b0535f7d8f7d158a3f4e",
    "board": {
      "key": "887595b735d68f0bc0b0b0535f7d8f7d158a3f4e",
      "name": "test_frontend",
      "type": "api",
      "subtype": "python",
      "environment": "production"
    },
    "name": "UX/UI designer",
    "url": "",
    "picture": null,
    "summary": "Are you passionate about designing for data-rich and complex interfaces? Can you balance business and competitive needs with the needs of end-users? Introduce simplicity into complexity and marry passion with practicality?\n\nIf that sounds like you, let’s talk. We’re looking for a Senior UX Designer to join our fast-moving team. Our product is constantly growing and expanding, so there’s ample opportunity to shape its future, weaving your own innovation and inspiration into the mix. We need someone who has imagination and vision, but who’s also able to buckle down to produce actionable designs.\n\nThis all happens alongside smart, funny, and competent colleagues. We value fun, accountability, mindfulness, integrity, love, and 'yes!' — our culture is as important to us as our product. Our reputation and vision are the strongest in our market and we’re backed by a seasoned executive team to help navigate our continued year-over-year growth.",
    "location": {
      "text": "Paris, France",
      "lat": 48.856614,
      "lng": 2.3522219,
      "gmaps": null,
      "fields": []
    },
    "archive": null,
    "archived_at": null,
    "updated_at": "2022-01-24T15:55:11+0000",
    "created_at": "2022-01-24T15:55:11+0000",
    "sections": [],
    "culture": null,
    "responsibilities": null,
    "requirements": null,
    "benefits": null,
    "interviews": null,
    "skills": [
      {
        "name": "Figma",
        "value": null,
        "type": null
      },
      {
        "name": "Photoshop",
        "value": null,
        "type": null
      },
      {
        "name": "Sketch",
        "value": null,
        "type": null
      },
      {
        "name": "Visual Communication",
        "value": null,
        "type": null
      },
      {
        "name": "Design",
        "value": null,
        "type": null
      },
      {
        "name": "Wireframing",
        "value": null,
        "type": null
      },
      {
        "name": "Prototyping",
        "value": null,
        "type": null
      }
    ],
    "languages": [
      {
        "name": "english",
        "value": null
      }
    ],
    "certifications": [],
    "courses": [],
    "tasks": [],
    "interests": [],
    "tags": [
      {
        "name": "company",
        "value": "HrFlow.ai"
      },
      {
        "name": "type",
        "value": "Full time"
      },
      {
        "name": "category",
        "value": "Human Resources"
      }
    ],
    "metadatas": [],
    "ranges_float": [],
    "ranges_date": [
      {
        "name": "",
        "value_min": "2023-06-13T22:59:59.999Z",
        "value_max": "2025-06-13T22:59:59.999Z"
      }
    ],
    "ref": {
      "current": {}
    }
  },
  {
    "id": 698217,
    "reference": null,
    "board_key": "887595b735d68f0bc0b0b0535f7d8f7d158a3f4e",
    "board": {
      "key": "887595b735d68f0bc0b0b0535f7d8f7d158a3f4e",
      "name": "test_frontend",
      "type": "api",
      "subtype": "python",
      "environment": "production"
    },
    "name": "DevOps Engineer",
    "url": "",
    "picture": null,
    "summary": "Developed a detailed understanding of our product infrastructure and identified areas for improvement\nHelped design new architectures and implement end-to-end automation\nSupported the development of numerous tools / systems to support our infrastructure goals\nHelp support our Kubernetes clusters\nResponded to ad-hoc requests from other engineering teams and enable them to work with our infrastructure and platforms",
    "location": {
      "text": "Casablanca, Morocco",
      "lat": 33.5731104,
      "lng": -7.5898434,
      "gmaps": null,
      "fields": []
    },
    "archive": null,
    "archived_at": null,
    "updated_at": "2022-01-24T15:55:10+0000",
    "created_at": "2022-01-24T15:55:10+0000",
    "sections": [],
    "culture": null,
    "responsibilities": null,
    "requirements": null,
    "benefits": null,
    "interviews": null,
    "skills": [
      {
        "name": "Containerization",
        "value": null,
        "type": null
      },
      {
        "name": "Docker",
        "value": null,
        "type": null
      },
      {
        "name": "Terraform",
        "value": null,
        "type": null
      },
      {
        "name": "Kubernetes",
        "value": null,
        "type": null
      },
      {
        "name": "Testing",
        "value": null,
        "type": null
      },
      {
        "name": "CI/CD",
        "value": null,
        "type": null
      },
      {
        "name": "Monitoring",
        "value": null,
        "type": null
      },
      {
        "name": "Python",
        "value": null,
        "type": null
      },
      {
        "name": "Yaml",
        "value": null,
        "type": null
      },
      {
        "name": "Scripting",
        "value": null,
        "type": null
      },
      {
        "name": "Shell",
        "value": null,
        "type": null
      }
    ],
    "languages": [
      {
        "name": "English",
        "value": null
      }
    ],
    "certifications": [],
    "courses": [],
    "tasks": [],
    "interests": [],
    "tags": [
      {
        "name": "company",
        "value": "HrFlow.ai"
      },
      {
        "name": "type",
        "value": "Full time"
      },
      {
        "name": "category",
        "value": "Software engineering"
      }
    ],
    "metadatas": [],
    "ranges_float": [],
    "ranges_date": [
      {
        "name": "",
        "value_min": "2021-12-24T22:59:59.999Z",
        "value_max": "2023-12-24T22:59:59.999Z"
      }
    ],
    "ref": {
      "current": {}
    }
  },
  {
    "id": 698216,
    "reference": null,
    "board_key": "887595b735d68f0bc0b0b0535f7d8f7d158a3f4e",
    "board": {
      "key": "887595b735d68f0bc0b0b0535f7d8f7d158a3f4e",
      "name": "test_frontend",
      "type": "api",
      "subtype": "python",
      "environment": "production"
    },
    "name": "Account Executive",
    "url": "",
    "picture": null,
    "summary": "The Account Executive, Small & Mid-Sized Business Sales will be responsible for building, managing and executing a territory specific sales pipeline. You will focus on building deep relationships with channel partners (Health Plan Account Managers, Benefits Consultants, other channel resellers), understanding the nuances of channel partner sales tactics and strategies, penetrating new enterprise opportunities all while managing the full, end-to-end sales process. And, of course, closing business.",
    "location": {
      "text": "San Francisco, CA, USA",
      "lat": 37.7749295,
      "lng": -122.4194155,
      "gmaps": null,
      "fields": []
    },
    "archive": null,
    "archived_at": null,
    "updated_at": "2022-01-24T15:55:09+0000",
    "created_at": "2022-01-24T15:55:09+0000",
    "sections": [],
    "culture": null,
    "responsibilities": null,
    "requirements": null,
    "benefits": null,
    "interviews": null,
    "skills": [
      {
        "name": "Sales",
        "value": null,
        "type": null
      },
      {
        "name": "Reporting",
        "value": null,
        "type": null
      },
      {
        "name": "CRM",
        "value": null,
        "type": null
      },
      {
        "name": "Marketing",
        "value": null,
        "type": null
      },
      {
        "name": "Negotiation",
        "value": null,
        "type": null
      },
      {
        "name": "Organization",
        "value": null,
        "type": null
      },
      {
        "name": "Problem solving",
        "value": null,
        "type": null
      },
      {
        "name": "Communication",
        "value": null,
        "type": null
      }
    ],
    "languages": [
      {
        "name": "english",
        "value": null
      }
    ],
    "certifications": [],
    "courses": [],
    "tasks": [],
    "interests": [],
    "tags": [
      {
        "name": "company",
        "value": "HrFlow.ai"
      },
      {
        "name": "type",
        "value": "Full time"
      },
      {
        "name": "category",
        "value": "Human resources"
      }
    ],
    "metadatas": [],
    "ranges_float": [],
    "ranges_date": [
      {
        "name": "",
        "value_min": "2021-12-24T22:59:59.999Z",
        "value_max": "2023-12-24T22:59:59.999Z"
      }
    ],
    "ref": {
      "current": {}
    }
  },
  {
    "id": 698215,
    "reference": null,
    "board_key": "887595b735d68f0bc0b0b0535f7d8f7d158a3f4e",
    "board": {
      "key": "887595b735d68f0bc0b0b0535f7d8f7d158a3f4e",
      "name": "test_frontend",
      "type": "api",
      "subtype": "python",
      "environment": "production"
    },
    "name": "Assistant Director, Digital Marketing",
    "url": "",
    "picture": null,
    "summary": "We’re looking for a Director of Digital Marketing to lead HrFlow.ai's digital marketing strategy. Reporting to the VP Marketing, you’ll be responsible for the design and development of HrFlow.ai, success of our earned and owned digital marketing campaigns, management of the advertising budget, execution of partner marketing programs, development of email nurtures, and the design and development of content and all creative assets. As a leader in the marketing team, you will ensure goals are established, plans are created and execution across all of HrFlow’s digital touchpoints are flawless. In this role you’ll manage a small team of digital marketers, our external design and development agencies, and work hand-in-hand with the product, product marketing, customer and partner marketing teams to ensure deadlines are met and goals are achieved. You’ll lead our Account Based Marketing approach and collaborate with the sales organization to ensure alignment on process, follow-up and messaging to prospects.",
    "location": {
      "text": "San Francisco, CA, USA",
      "lat": 37.7749295,
      "lng": -122.4194155,
      "gmaps": null,
      "fields": []
    },
    "archive": null,
    "archived_at": null,
    "updated_at": "2022-01-24T15:55:08+0000",
    "created_at": "2022-01-24T15:55:08+0000",
    "sections": [],
    "culture": null,
    "responsibilities": null,
    "requirements": null,
    "benefits": null,
    "interviews": null,
    "skills": [
      {
        "name": "Marketing",
        "value": null,
        "type": null
      },
      {
        "name": "Data analysis",
        "value": null,
        "type": null
      },
      {
        "name": "SEO",
        "value": null,
        "type": null
      },
      {
        "name": " Social advertising",
        "value": null,
        "type": null
      },
      {
        "name": "Social media marketing",
        "value": null,
        "type": null
      },
      {
        "name": "Account segmentation",
        "value": null,
        "type": null
      },
      {
        "name": "MRM",
        "value": null,
        "type": null
      },
      {
        "name": "CRM",
        "value": null,
        "type": null
      }
    ],
    "languages": [
      {
        "name": "English",
        "value": null
      }
    ],
    "certifications": [],
    "courses": [],
    "tasks": [],
    "interests": [],
    "tags": [
      {
        "name": "company",
        "value": "HrFlow.ai"
      },
      {
        "name": "type",
        "value": "Full time"
      },
      {
        "name": "category",
        "value": "Financial Services"
      }
    ],
    "metadatas": [],
    "ranges_float": [],
    "ranges_date": [
      {
        "name": "",
        "value_min": "2021-12-24T22:59:59.999Z",
        "value_max": "2023-12-24T22:59:59.999Z"
      }
    ],
    "ref": {
      "current": {}
    }
  },
  {
    "id": 698214,
    "reference": null,
    "board_key": "887595b735d68f0bc0b0b0535f7d8f7d158a3f4e",
    "board": {
      "key": "887595b735d68f0bc0b0b0535f7d8f7d158a3f4e",
      "name": "test_frontend",
      "type": "api",
      "subtype": "python",
      "environment": "production"
    },
    "name": "Java Developer",
    "url": "",
    "picture": null,
    "summary": "Create a clear and compelling medium and long-term vision for the product you own and develop a roadmap to realize that vision\nDrive the product development process for your product from ideation to launch to impact analysis, collaborating with many teams along the way\nUse data to discover and justify investments as well as to analyze their impact\nPartner closely with our Operations and Engineering teams to ensure the problem space is well understood and solutions built have the intended impact\nContribute to mentoring the teams and our process to improve the impact that the product organization has\nDefine OKRs, track progress, and measure the impact of the team’s efforts against business goals\nBe a positive contributor to the Product team at large, e.g., help foster an environment of continuous learning, mentor team members, etc.",
    "location": {
      "text": "Paris, France",
      "lat": 48.856614,
      "lng": 2.3522219,
      "gmaps": null,
      "fields": []
    },
    "archive": null,
    "archived_at": null,
    "updated_at": "2022-01-24T15:55:07+0000",
    "created_at": "2022-01-24T15:55:07+0000",
    "sections": [],
    "culture": null,
    "responsibilities": null,
    "requirements": null,
    "benefits": null,
    "interviews": null,
    "skills": [
      {
        "name": "Management",
        "value": null,
        "type": null
      },
      {
        "name": "SaaS",
        "value": null,
        "type": null
      },
      {
        "name": "API",
        "value": null,
        "type": null
      },
      {
        "name": "SDK",
        "value": null,
        "type": null
      },
      {
        "name": "Scrum",
        "value": null,
        "type": null
      },
      {
        "name": "UX",
        "value": null,
        "type": null
      },
      {
        "name": "Testing",
        "value": null,
        "type": null
      },
      {
        "name": "UI",
        "value": null,
        "type": null
      },
      {
        "name": "Strategic thinking",
        "value": null,
        "type": null
      }
    ],
    "languages": [
      {
        "name": "english",
        "value": null
      }
    ],
    "certifications": [],
    "courses": [],
    "tasks": [],
    "interests": [],
    "tags": [
      {
        "name": "company",
        "value": "HrFlow.ai"
      },
      {
        "name": "type",
        "value": "Full time"
      },
      {
        "name": "category",
        "value": "Software engineering"
      }
    ],
    "metadatas": [],
    "ranges_float": [],
    "ranges_date": [
      {
        "name": "",
        "value_min": "2021-12-24T22:59:59.999Z",
        "value_max": "2023-12-24T22:59:59.999Z"
      }
    ],
    "ref": {
      "current": {}
    }
  },
  {
    "id": 698213,
    "reference": null,
    "board_key": "887595b735d68f0bc0b0b0535f7d8f7d158a3f4e",
    "board": {
      "key": "887595b735d68f0bc0b0b0535f7d8f7d158a3f4e",
      "name": "test_frontend",
      "type": "api",
      "subtype": "python",
      "environment": "production"
    },
    "name": "AI Engineer",
    "url": "",
    "picture": null,
    "summary": "Be part of a team that builds impactful features for our customers and pros everyday\nCollaborate with product and business teams to review specs and breakdown features into releasable chunks and work on those features\nContribute to code reviews, architectural and design reviews, evangelize best engineering practices, and participate in Handy lunch & learn sessions\nBe part of our production on-call rotation to support what you built.\nA skillful engineer with at least 3+ years of full-time, hands-on experience in a web stack\nWell-versed in at least one object oriented programming language: Ruby, Python, etc.\nAlways eager to understand and solve impactful business problems\nA great collaborator with both technical and non-technical team members\nHave a good foundational knowledge of programming languages, databases, operating systems, data structures, algorithms, and complexity trade-offs\nHaving worked at or founded a growth-stage startup is a plus Compensation & Benefits\nCompetitive salary and equity commensurate with experience and performance\nFull medical, dental, vision package to fit your needs\nMonthly Handy credits\nUnlimited vacation policy; work hard and take time when you need it\nA fun office, always stocked with coffee, snacks and drinks; catered lunch and dinner, foosball, office events and team outings\nGround floor opportunity with the team\nThe rare opportunity to work with sharp, motivated teammates solving some of the most unique challenges and changing the world We are an equal opportunity employer and value diversity at our company. We do not discriminate on the basis of race, religion, color, national origin, gender, sexual orientation, age, marital status, veteran status, or disability status.",
    "location": {
      "text": "Paris, France",
      "lat": 48.856614,
      "lng": 2.3522219,
      "gmaps": null,
      "fields": []
    },
    "archive": null,
    "archived_at": null,
    "updated_at": "2022-01-24T15:55:06+0000",
    "created_at": "2022-01-24T15:55:06+0000",
    "sections": [],
    "culture": null,
    "responsibilities": null,
    "requirements": null,
    "benefits": null,
    "interviews": null,
    "skills": [
      {
        "name": "Python",
        "value": null,
        "type": null
      },
      {
        "name": "Javascript",
        "value": null,
        "type": null
      },
      {
        "name": "HTML",
        "value": null,
        "type": null
      },
      {
        "name": "CSS",
        "value": null,
        "type": null
      },
      {
        "name": "CI/CD",
        "value": null,
        "type": null
      },
      {
        "name": "PHP",
        "value": null,
        "type": null
      },
      {
        "name": "Java",
        "value": null,
        "type": null
      },
      {
        "name": "Problem solving",
        "value": null,
        "type": null
      },
      {
        "name": "Mysql",
        "value": null,
        "type": null
      },
      {
        "name": "Mongodb",
        "value": null,
        "type": null
      }
    ],
    "languages": [
      {
        "name": "english",
        "value": null
      }
    ],
    "certifications": [],
    "courses": [],
    "tasks": [],
    "interests": [],
    "tags": [
      {
        "name": "company",
        "value": "Hrflow.ai"
      },
      {
        "name": "type",
        "value": "Full time"
      },
      {
        "name": "category",
        "value": "Artificial intelligence"
      }
    ],
    "metadatas": [],
    "ranges_float": [],
    "ranges_date": [
      {
        "name": "",
        "value_min": "2021-12-24T22:59:59.999Z",
        "value_max": "2023-12-24T22:59:59.999Z"
      }
    ],
    "ref": {
      "current": {}
    }
  },
  {
    "id": 698212,
    "reference": null,
    "board_key": "887595b735d68f0bc0b0b0535f7d8f7d158a3f4e",
    "board": {
      "key": "887595b735d68f0bc0b0b0535f7d8f7d158a3f4e",
      "name": "test_frontend",
      "type": "api",
      "subtype": "python",
      "environment": "production"
    },
    "name": "Data Scientist",
    "url": "",
    "picture": null,
    "summary": "",
    "location": {
      "text": "Paris, France",
      "lat": 48.856614,
      "lng": 2.3522219,
      "gmaps": null,
      "fields": []
    },
    "archive": null,
    "archived_at": null,
    "updated_at": "2022-01-24T15:55:05+0000",
    "created_at": "2022-01-24T15:55:05+0000",
    "sections": [
      {
        "name": "",
        "title": "",
        "description": "3+ years hands-on experience as a data scientist.\nUnder the hood knowledge with a variety of ML algorithms.\nMSc. in Statistics, Computer Science, Mathematics or other quantitative field.\nAbility to work independently and deliver end-to-end output.\nTeam player, can-do attitude, collaborative, good communication skills"
      }
    ],
    "culture": null,
    "responsibilities": null,
    "requirements": null,
    "benefits": null,
    "interviews": null,
    "skills": [
      {
        "name": "python",
        "value": null,
        "type": null
      },
      {
        "name": "R",
        "value": null,
        "type": null
      },
      {
        "name": "data visualisation",
        "value": null,
        "type": null
      },
      {
        "name": "linear algebra",
        "value": null,
        "type": null
      },
      {
        "name": "machine learning",
        "value": null,
        "type": null
      },
      {
        "name": "deep learning ",
        "value": null,
        "type": null
      },
      {
        "name": "NLP",
        "value": null,
        "type": null
      }
    ],
    "languages": [
      {
        "name": "english",
        "value": null
      }
    ],
    "certifications": [],
    "courses": [],
    "tasks": [],
    "interests": [],
    "tags": [
      {
        "name": "company",
        "value": "HrFlow.ai"
      },
      {
        "name": "type",
        "value": "Full time"
      },
      {
        "name": "category",
        "value": "AI / Research & Development"
      }
    ],
    "metadatas": [],
    "ranges_float": [],
    "ranges_date": [
      {
        "name": "",
        "value_min": "2021-12-24T22:59:59.999Z",
        "value_max": "2023-12-24T22:59:59.999Z"
      }
    ],
    "ref": {
      "current": {}
    }
  },
  {
    "id": 698211,
    "reference": null,
    "board_key": "887595b735d68f0bc0b0b0535f7d8f7d158a3f4e",
    "board": {
      "key": "887595b735d68f0bc0b0b0535f7d8f7d158a3f4e",
      "name": "test_frontend",
      "type": "api",
      "subtype": "python",
      "environment": "production"
    },
    "name": "UX designer",
    "url": "",
    "picture": null,
    "summary": "Are you passionate about designing for data-rich and complex interfaces? Can you balance business and competitive needs with the needs of end-users? Introduce simplicity into complexity and marry passion with practicality?\n\nIf that sounds like you, let’s talk. We’re looking for a Senior UX Designer to join our fast-moving team. Our product is constantly growing and expanding, so there’s ample opportunity to shape its future, weaving your own innovation and inspiration into the mix. We need someone who has imagination and vision, but who’s also able to buckle down to produce actionable designs.\n\nThis all happens alongside smart, funny, and competent colleagues. We value fun, accountability, mindfulness, integrity, love, and 'yes!' — our culture is as important to us as our product. Our reputation and vision are the strongest in our market and we’re backed by a seasoned executive team to help navigate our continued year-over-year growth.",
    "location": {
      "text": "Paris, France",
      "lat": 48.856614,
      "lng": 2.3522219,
      "gmaps": null,
      "fields": []
    },
    "archive": null,
    "archived_at": null,
    "updated_at": "2022-01-24T15:55:04+0000",
    "created_at": "2022-01-24T15:55:04+0000",
    "sections": [],
    "culture": null,
    "responsibilities": null,
    "requirements": null,
    "benefits": null,
    "interviews": null,
    "skills": [
      {
        "name": "Figma",
        "value": null,
        "type": null
      },
      {
        "name": "Photoshop",
        "value": null,
        "type": null
      },
      {
        "name": "Sketch",
        "value": null,
        "type": null
      },
      {
        "name": "Visual Communication",
        "value": null,
        "type": null
      },
      {
        "name": "Design",
        "value": null,
        "type": null
      },
      {
        "name": "Wireframing",
        "value": null,
        "type": null
      },
      {
        "name": "Prototyping",
        "value": null,
        "type": null
      }
    ],
    "languages": [
      {
        "name": "english",
        "value": null
      }
    ],
    "certifications": [],
    "courses": [],
    "tasks": [],
    "interests": [],
    "tags": [
      {
        "name": "company",
        "value": "HrFlow.ai"
      },
      {
        "name": "type",
        "value": "Full time"
      },
      {
        "name": "category",
        "value": "Humain Resources"
      }
    ],
    "metadatas": [],
    "ranges_float": [],
    "ranges_date": [
      {
        "name": "",
        "value_min": "2021-12-24T22:59:59.999Z",
        "value_max": "2023-12-24T22:59:59.999Z"
      }
    ],
    "ref": {
      "current": {}
    }
  },
  {
    "id": 698210,
    "reference": null,
    "board_key": "887595b735d68f0bc0b0b0535f7d8f7d158a3f4e",
    "board": {
      "key": "887595b735d68f0bc0b0b0535f7d8f7d158a3f4e",
      "name": "test_frontend",
      "type": "api",
      "subtype": "python",
      "environment": "production"
    },
    "name": "Senior DevOps Engineer",
    "url": "",
    "picture": null,
    "summary": "Developed a detailed understanding of our product infrastructure and identified areas for improvement\nHelped design new architectures and implement end-to-end automation\nSupported the development of numerous tools / systems to support our infrastructure goals\nHelp support our Kubernetes clusters\nResponded to ad-hoc requests from other engineering teams and enable them to work with our infrastructure and platforms",
    "location": {
      "text": "Casablanca, Morocco",
      "lat": 33.5731104,
      "lng": -7.5898434,
      "gmaps": null,
      "fields": []
    },
    "archive": null,
    "archived_at": null,
    "updated_at": "2022-01-24T15:55:03+0000",
    "created_at": "2022-01-24T15:55:03+0000",
    "sections": [],
    "culture": null,
    "responsibilities": null,
    "requirements": null,
    "benefits": null,
    "interviews": null,
    "skills": [
      {
        "name": "Containerization",
        "value": null,
        "type": null
      },
      {
        "name": "Docker",
        "value": null,
        "type": null
      },
      {
        "name": "Terraform",
        "value": null,
        "type": null
      },
      {
        "name": "Kubernetes",
        "value": null,
        "type": null
      },
      {
        "name": "Testing",
        "value": null,
        "type": null
      },
      {
        "name": "CI/CD",
        "value": null,
        "type": null
      },
      {
        "name": "Monitoring",
        "value": null,
        "type": null
      },
      {
        "name": "Python",
        "value": null,
        "type": null
      },
      {
        "name": "Yaml",
        "value": null,
        "type": null
      },
      {
        "name": "Scripting",
        "value": null,
        "type": null
      },
      {
        "name": "Shell",
        "value": null,
        "type": null
      }
    ],
    "languages": [
      {
        "name": "English",
        "value": null
      }
    ],
    "certifications": [],
    "courses": [],
    "tasks": [],
    "interests": [],
    "tags": [
      {
        "name": "company",
        "value": "HrFlow.ai"
      },
      {
        "name": "type",
        "value": "Full time"
      },
      {
        "name": "category",
        "value": "Software engineering"
      }
    ],
    "metadatas": [],
    "ranges_float": [],
    "ranges_date": [
      {
        "name": "",
        "value_min": "2021-12-24T22:59:59.999Z",
        "value_max": "2023-12-24T22:59:59.999Z"
      }
    ],
    "ref": {
      "current": null
    }
  },
  {
    "id": 698209,
    "reference": null,
    "board_key": "887595b735d68f0bc0b0b0535f7d8f7d158a3f4e",
    "board": {
      "key": "887595b735d68f0bc0b0b0535f7d8f7d158a3f4e",
      "name": "test_frontend",
      "type": "api",
      "subtype": "python",
      "environment": "production"
    },
    "name": "Account Executive, Small & Mid-Sized Business Sales",
    "url": "",
    "picture": null,
    "summary": "The Account Executive, Small & Mid-Sized Business Sales will be responsible for building, managing and executing a territory specific sales pipeline. You will focus on building deep relationships with channel partners (Health Plan Account Managers, Benefits Consultants, other channel resellers), understanding the nuances of channel partner sales tactics and strategies, penetrating new enterprise opportunities all while managing the full, end-to-end sales process. And, of course, closing business.",
    "location": {
      "text": "San Francisco, CA, USA",
      "lat": 37.7749295,
      "lng": -122.4194155,
      "gmaps": null,
      "fields": []
    },
    "archive": null,
    "archived_at": null,
    "updated_at": "2022-01-24T15:55:02+0000",
    "created_at": "2022-01-24T15:55:02+0000",
    "sections": [],
    "culture": null,
    "responsibilities": null,
    "requirements": null,
    "benefits": null,
    "interviews": null,
    "skills": [
      {
        "name": "Sales",
        "value": null,
        "type": null
      },
      {
        "name": "Reporting",
        "value": null,
        "type": null
      },
      {
        "name": "CRM",
        "value": null,
        "type": null
      },
      {
        "name": "Marketing",
        "value": null,
        "type": null
      },
      {
        "name": "Negotiation",
        "value": null,
        "type": null
      },
      {
        "name": "Organization",
        "value": null,
        "type": null
      },
      {
        "name": "Problem solving",
        "value": null,
        "type": null
      },
      {
        "name": "Communication",
        "value": null,
        "type": null
      }
    ],
    "languages": [
      {
        "name": "english",
        "value": null
      }
    ],
    "certifications": [],
    "courses": [],
    "tasks": [],
    "interests": [],
    "tags": [
      {
        "name": "company",
        "value": "HrFlow.ai"
      },
      {
        "name": "type",
        "value": "Full time"
      },
      {
        "name": "category",
        "value": "Human resources"
      }
    ],
    "metadatas": [],
    "ranges_float": [],
    "ranges_date": [
      {
        "name": "",
        "value_min": "2021-12-24T22:59:59.999Z",
        "value_max": "2023-12-24T22:59:59.999Z"
      }
    ],
    "ref": {
      "current": null
    }
  },
  {
    "id": 698208,
    "reference": null,
    "board_key": "887595b735d68f0bc0b0b0535f7d8f7d158a3f4e",
    "board": {
      "key": "887595b735d68f0bc0b0b0535f7d8f7d158a3f4e",
      "name": "test_frontend",
      "type": "api",
      "subtype": "python",
      "environment": "production"
    },
    "name": "Director, Digital Marketing",
    "url": "",
    "picture": null,
    "summary": "We’re looking for a Director of Digital Marketing to lead HrFlow.ai's digital marketing strategy. Reporting to the VP Marketing, you’ll be responsible for the design and development of HrFlow.ai, success of our earned and owned digital marketing campaigns, management of the advertising budget, execution of partner marketing programs, development of email nurtures, and the design and development of content and all creative assets. As a leader in the marketing team, you will ensure goals are established, plans are created and execution across all of HrFlow’s digital touchpoints are flawless. In this role you’ll manage a small team of digital marketers, our external design and development agencies, and work hand-in-hand with the product, product marketing, customer and partner marketing teams to ensure deadlines are met and goals are achieved. You’ll lead our Account Based Marketing approach and collaborate with the sales organization to ensure alignment on process, follow-up and messaging to prospects.",
    "location": {
      "text": "San Francisco, CA, USA",
      "lat": 37.7749295,
      "lng": -122.4194155,
      "gmaps": null,
      "fields": []
    },
    "archive": null,
    "archived_at": null,
    "updated_at": "2022-01-24T15:55:01+0000",
    "created_at": "2022-01-24T15:55:01+0000",
    "sections": [],
    "culture": null,
    "responsibilities": null,
    "requirements": null,
    "benefits": null,
    "interviews": null,
    "skills": [
      {
        "name": "Marketing",
        "value": null,
        "type": null
      },
      {
        "name": "Data analysis",
        "value": null,
        "type": null
      },
      {
        "name": "SEO",
        "value": null,
        "type": null
      },
      {
        "name": " Social advertising",
        "value": null,
        "type": null
      },
      {
        "name": "Social media marketing",
        "value": null,
        "type": null
      },
      {
        "name": "Account segmentation",
        "value": null,
        "type": null
      },
      {
        "name": "MRM",
        "value": null,
        "type": null
      },
      {
        "name": "CRM",
        "value": null,
        "type": null
      }
    ],
    "languages": [
      {
        "name": "English",
        "value": null
      }
    ],
    "certifications": [],
    "courses": [],
    "tasks": [],
    "interests": [],
    "tags": [
      {
        "name": "company",
        "value": "HrFlow.ai"
      },
      {
        "name": "type",
        "value": "Full time"
      },
      {
        "name": "category",
        "value": "Financial Services"
      }
    ],
    "metadatas": [],
    "ranges_float": [],
    "ranges_date": [
      {
        "name": "",
        "value_min": "2021-12-24T22:59:59.999Z",
        "value_max": "2023-12-24T22:59:59.999Z"
      }
    ],
    "ref": {
      "current": null
    }
  },
  {
    "id": 698207,
    "reference": null,
    "board_key": "887595b735d68f0bc0b0b0535f7d8f7d158a3f4e",
    "board": {
      "key": "887595b735d68f0bc0b0b0535f7d8f7d158a3f4e",
      "name": "test_frontend",
      "type": "api",
      "subtype": "python",
      "environment": "production"
    },
    "name": "Product Manager",
    "url": "",
    "picture": null,
    "summary": "Create a clear and compelling medium and long-term vision for the product you own and develop a roadmap to realize that vision\nDrive the product development process for your product from ideation to launch to impact analysis, collaborating with many teams along the way\nUse data to discover and justify investments as well as to analyze their impact\nPartner closely with our Operations and Engineering teams to ensure the problem space is well understood and solutions built have the intended impact\nContribute to mentoring the teams and our process to improve the impact that the product organization has\nDefine OKRs, track progress, and measure the impact of the team’s efforts against business goals\nBe a positive contributor to the Product team at large, e.g., help foster an environment of continuous learning, mentor team members, etc.",
    "location": {
      "text": "Paris, France",
      "lat": 48.856614,
      "lng": 2.3522219,
      "gmaps": null,
      "fields": []
    },
    "archive": null,
    "archived_at": null,
    "updated_at": "2022-01-24T15:55:00+0000",
    "created_at": "2022-01-24T15:55:00+0000",
    "sections": [],
    "culture": null,
    "responsibilities": null,
    "requirements": null,
    "benefits": null,
    "interviews": null,
    "skills": [
      {
        "name": "Management",
        "value": null,
        "type": null
      },
      {
        "name": "SaaS",
        "value": null,
        "type": null
      },
      {
        "name": "API",
        "value": null,
        "type": null
      },
      {
        "name": "SDK",
        "value": null,
        "type": null
      },
      {
        "name": "Scrum",
        "value": null,
        "type": null
      },
      {
        "name": "UX",
        "value": null,
        "type": null
      },
      {
        "name": "Testing",
        "value": null,
        "type": null
      },
      {
        "name": "UI",
        "value": null,
        "type": null
      },
      {
        "name": "Strategic thinking",
        "value": null,
        "type": null
      }
    ],
    "languages": [
      {
        "name": "english",
        "value": null
      }
    ],
    "certifications": [],
    "courses": [],
    "tasks": [],
    "interests": [],
    "tags": [
      {
        "name": "company",
        "value": "HrFlow.ai"
      },
      {
        "name": "type",
        "value": "Full time"
      },
      {
        "name": "category",
        "value": "Software engineering"
      }
    ],
    "metadatas": [],
    "ranges_float": [],
    "ranges_date": [
      {
        "name": "",
        "value_min": "2021-12-24T22:59:59.999Z",
        "value_max": "2023-12-24T22:59:59.999Z"
      }
    ],
    "ref": {
      "current": null
    }
  },
  {
    "id": 698206,
    "reference": null,
    "board_key": "887595b735d68f0bc0b0b0535f7d8f7d158a3f4e",
    "board": {
      "key": "887595b735d68f0bc0b0b0535f7d8f7d158a3f4e",
      "name": "test_frontend",
      "type": "api",
      "subtype": "python",
      "environment": "production"
    },
    "name": "Software Engineer",
    "url": "",
    "picture": null,
    "summary": "Be part of a team that builds impactful features for our customers and pros everyday\nCollaborate with product and business teams to review specs and breakdown features into releasable chunks and work on those features\nContribute to code reviews, architectural and design reviews, evangelize best engineering practices, and participate in Handy lunch & learn sessions\nBe part of our production on-call rotation to support what you built.\nA skillful engineer with at least 3+ years of full-time, hands-on experience in a web stack\nWell-versed in at least one object oriented programming language: Ruby, Python, etc.\nAlways eager to understand and solve impactful business problems\nA great collaborator with both technical and non-technical team members\nHave a good foundational knowledge of programming languages, databases, operating systems, data structures, algorithms, and complexity trade-offs\nHaving worked at or founded a growth-stage startup is a plus Compensation & Benefits\nCompetitive salary and equity commensurate with experience and performance\nFull medical, dental, vision package to fit your needs\nMonthly Handy credits\nUnlimited vacation policy; work hard and take time when you need it\nA fun office, always stocked with coffee, snacks and drinks; catered lunch and dinner, foosball, office events and team outings\nGround floor opportunity with the team\nThe rare opportunity to work with sharp, motivated teammates solving some of the most unique challenges and changing the world We are an equal opportunity employer and value diversity at our company. We do not discriminate on the basis of race, religion, color, national origin, gender, sexual orientation, age, marital status, veteran status, or disability status.",
    "location": {
      "text": "Paris, France",
      "lat": 48.856614,
      "lng": 2.3522219,
      "gmaps": null,
      "fields": []
    },
    "archive": null,
    "archived_at": null,
    "updated_at": "2022-01-24T15:54:59+0000",
    "created_at": "2022-01-24T15:54:59+0000",
    "sections": [],
    "culture": null,
    "responsibilities": null,
    "requirements": null,
    "benefits": null,
    "interviews": null,
    "skills": [
      {
        "name": "Python",
        "value": null,
        "type": null
      },
      {
        "name": "Javascript",
        "value": null,
        "type": null
      },
      {
        "name": "HTML",
        "value": null,
        "type": null
      },
      {
        "name": "CSS",
        "value": null,
        "type": null
      },
      {
        "name": "CI/CD",
        "value": null,
        "type": null
      },
      {
        "name": "PHP",
        "value": null,
        "type": null
      },
      {
        "name": "Java",
        "value": null,
        "type": null
      },
      {
        "name": "Problem solving",
        "value": null,
        "type": null
      },
      {
        "name": "Mysql",
        "value": null,
        "type": null
      },
      {
        "name": "Mongodb",
        "value": null,
        "type": null
      }
    ],
    "languages": [
      {
        "name": "english",
        "value": null
      }
    ],
    "certifications": [],
    "courses": [],
    "tasks": [],
    "interests": [],
    "tags": [
      {
        "name": "company",
        "value": "Hrflow.ai"
      },
      {
        "name": "type",
        "value": "Full time"
      },
      {
        "name": "category",
        "value": "Artificial intelligence"
      }
    ],
    "metadatas": [],
    "ranges_float": [],
    "ranges_date": [
      {
        "name": "",
        "value_min": "2021-12-24T22:59:59.999Z",
        "value_max": "2023-12-24T22:59:59.999Z"
      }
    ],
    "ref": {
      "current": null
    }
  }
]
